gitannexgui/__init__.py
gitannexgui/__main__.py
gitannexgui/app.py
gitannexgui/gitannex.py
gitannexgui/main.qml
gitannexgui/qml.rcc
git_annex_gui-0.2.8.dist-info/LICENSE
git_annex_gui-0.2.8.dist-info/METADATA
git_annex_gui-0.2.8.dist-info/WHEEL
git_annex_gui-0.2.8.dist-info/entry_points.txt
git_annex_gui-0.2.8.dist-info/top_level.txt
git_annex_gui-0.2.8.dist-info/RECORD
