Metadata-Version: 2.1
Name: git-annex-gui
Version: 0.2.8
Summary: A small systray app for git annex assistant.
Home-page: https://gitlab.com/joystein/git-annex-gui
Author: Øystein S. Haaland
Author-email: oystein.s.haaland@gmail.com
License: UNKNOWN
Platform: UNKNOWN
Requires-Dist: PySide2
Provides-Extra: dev
Requires-Dist: invoke ; extra == 'dev'
Requires-Dist: pytest ; extra == 'dev'
Requires-Dist: python-language-server ; extra == 'dev'
Requires-Dist: restview ; extra == 'dev'
